<?xml version="1.0" encoding="UTF-8"?>
<PathOfBuilding>
	<Build level="12" targetVersion="3_0" pantheonMajorGod="None" bandit="None" className="Duelist" ascendClassName="None" mainSocketGroup="1" viewMode="SKILLS" pantheonMinorGod="None">
		<PlayerStat stat="CombinedDPS" value="0"/>
		<PlayerStat stat="Str" value="73"/>
		<PlayerStat stat="ReqStr" value="29"/>
		<PlayerStat stat="Dex" value="43"/>
		<PlayerStat stat="ReqDex" value="33"/>
		<PlayerStat stat="Int" value="44"/>
		<PlayerStat stat="Devotion" value="0"/>
		<PlayerStat stat="TotalEHP" value="1208.0536912752"/>
		<PlayerStat stat="PhysicalMaximumHitTaken" value="802.43902439024"/>
		<PlayerStat stat="LightningMaximumHitTaken" value="329"/>
		<PlayerStat stat="FireMaximumHitTaken" value="329"/>
		<PlayerStat stat="ColdMaximumHitTaken" value="329"/>
		<PlayerStat stat="ChaosMaximumHitTaken" value="329"/>
		<PlayerStat stat="Life" value="329"/>
		<PlayerStat stat="Spec:LifeInc" value="8"/>
		<PlayerStat stat="LifeUnreserved" value="329"/>
		<PlayerStat stat="LifeRecoverable" value="329"/>
		<PlayerStat stat="LifeUnreservedPercent" value="100"/>
		<PlayerStat stat="LifeRegenRecovery" value="3.29"/>
		<PlayerStat stat="Mana" value="202"/>
		<PlayerStat stat="Spec:ManaInc" value="32"/>
		<PlayerStat stat="ManaUnreserved" value="153"/>
		<PlayerStat stat="ManaUnreservedPercent" value="75.742574257426"/>
		<PlayerStat stat="ManaRegenRecovery" value="6.2"/>
		<PlayerStat stat="Ward" value="0"/>
		<PlayerStat stat="EnergyShield" value="0"/>
		<PlayerStat stat="EnergyShieldRecoveryCap" value="0"/>
		<PlayerStat stat="Spec:EnergyShieldInc" value="0"/>
		<PlayerStat stat="EnergyShieldRegenRecovery" value="0"/>
		<PlayerStat stat="Evasion" value="295"/>
		<PlayerStat stat="Spec:EvasionInc" value="12"/>
		<PlayerStat stat="MeleeEvadeChance" value="51"/>
		<PlayerStat stat="ProjectileEvadeChance" value="51"/>
		<PlayerStat stat="Armour" value="148"/>
		<PlayerStat stat="Spec:ArmourInc" value="12"/>
		<PlayerStat stat="PhysicalDamageReduction" value="59"/>
		<PlayerStat stat="BlockChance" value="23"/>
		<PlayerStat stat="SpellBlockChance" value="0"/>
		<PlayerStat stat="AttackDodgeChance" value="0"/>
		<PlayerStat stat="SpellDodgeChance" value="0"/>
		<PlayerStat stat="SpellSuppressionChance" value="0"/>
		<PlayerStat stat="FireResist" value="0"/>
		<PlayerStat stat="FireResistOverCap" value="0"/>
		<PlayerStat stat="ColdResist" value="0"/>
		<PlayerStat stat="ColdResistOverCap" value="0"/>
		<PlayerStat stat="LightningResist" value="0"/>
		<PlayerStat stat="LightningResistOverCap" value="0"/>
		<PlayerStat stat="ChaosResist" value="0"/>
		<PlayerStat stat="ChaosResistOverCap" value="0"/>
		<PlayerStat stat="EffectiveMovementSpeedMod" value="1.2"/>
		<PlayerStat stat="FullDPS" value="211.18648409257"/>
		<PlayerStat stat="FullDotDPS" value="25.726146945776"/>
		<FullDPSSkill skillPart="" source="" stat="Shield Charge" value="126.9485773936"/>
		<FullDPSSkill skillPart="No Flask" source="" stat="Poisonous Concoction" value="58.511759753197"/>
		<FullDPSSkill skillPart="" source="" stat="Full Poison DPS" value="15.13770048"/>
		<FullDPSSkill skillPart="" source="Shield Charge" stat="Best Ignite DPS" value="10.588446465776"/>
		<PlayerStat stat="PowerCharges" value="0"/>
		<PlayerStat stat="PowerChargesMax" value="3"/>
		<PlayerStat stat="FrenzyCharges" value="0"/>
		<PlayerStat stat="FrenzyChargesMax" value="3"/>
		<PlayerStat stat="EnduranceCharges" value="0"/>
		<PlayerStat stat="EnduranceChargesMax" value="3"/>
		<PlayerStat stat="ActiveTotemLimit" value="1"/>
		<TimelessData searchList="" searchListFallback=""/>
	</Build>
	<Import/>
	<Calcs>
		<Input name="misc_buffMode" string="EFFECTIVE"/>
		<Input name="skill_number" number="1"/>
		<Section subsection="ViewSkillDetails" collapsed="false" id="SkillSelect"/>
		<Section subsection="SkillHitDamage" collapsed="false" id="HitDamage"/>
		<Section subsection="ExertingWarcries" collapsed="false" id="Warcries"/>
		<Section subsection="SkillDamageoverTime" collapsed="false" id="Dot"/>
		<Section subsection="AttackCastRate" collapsed="false" id="Speed"/>
		<Section subsection="Crits" collapsed="false" id="Crit"/>
		<Section subsection="Impale" collapsed="false" id="Impale"/>
		<Section subsection="SkilltypespecificStats" collapsed="false" id="SkillTypeStats"/>
		<Section subsection="Accuracy" collapsed="false" id="HitChance"/>
		<Section subsection="Bleed" collapsed="false" id="Bleed"/>
		<Section subsection="Poison" collapsed="false" id="Poison"/>
		<Section subsection="Ignite" collapsed="false" id="Ignite"/>
		<Section subsection="Decay" collapsed="false" id="Decay"/>
		<Section subsection="LeechGainonHit" collapsed="false" id="LeechGain"/>
		<Section subsection="NonDamagingAilments" collapsed="false" id="EleAilments"/>
		<Section subsection="OtherEffects" collapsed="false" id="MiscEffects"/>
		<Section subsection="Attributes" collapsed="false" id="Attributes"/>
		<Section subsection="Life" collapsed="false" id="Life"/>
		<Section subsection="Mana" collapsed="false" id="Mana"/>
		<Section subsection="EnergyShield" collapsed="false" id="EnergyShield"/>
		<Section subsection="Ward" collapsed="false" id="Ward"/>
		<Section subsection="Armour" collapsed="false" id="Armour"/>
		<Section subsection="Evasion" collapsed="false" id="Evasion"/>
		<Section subsection="Resists" collapsed="false" id="Resist"/>
		<Section subsection="Block" collapsed="false" id="Block"/>
		<Section subsection="GainonBlock" collapsed="true" id="Block"/>
		<Section subsection="OtherDefences" collapsed="false" id="MiscDefences"/>
		<Section subsection="StunDuration" collapsed="false" id="MiscDefences"/>
		<Section subsection="DamageAvoidance" collapsed="false" id="MiscDefences"/>
		<Section subsection="OtherAvoidance" collapsed="true" id="MiscDefences"/>
		<Section subsection="OtherAilmentDefences" collapsed="true" id="MiscDefences"/>
		<Section subsection="Dodge" collapsed="false" id="MiscDefences"/>
		<Section subsection="SpellSuppression" collapsed="false" id="MiscDefences"/>
		<Section subsection="DamageTaken" collapsed="false" id="DamageTaken"/>
		<Section subsection="DamagingHits" collapsed="false" id="DamageTaken"/>
		<Section subsection="EffectiveHealthPool" collapsed="false" id="DamageTaken"/>
		<Section subsection="MaximumHitTaken" collapsed="false" id="DamageTaken"/>
		<Section subsection="DotsandDegens" collapsed="false" id="DamageTaken"/>
	</Calcs>
	<Skills sortGemsByDPSField="FullDPS" matchGemLevelToCharacterLevel="false" activeSkillSet="2" sortGemsByDPS="true" defaultGemQuality="0" defaultGemLevel="1" showSupportGemTypes="NORMAL" showAltQualityGems="false">
		<SkillSet title="lvl12 Merveil Splitting Steel" id="2">
			<Skill mainActiveSkillCalcs="1" includeInFullDPS="true" label="Splitting Steel [GGR]" enabled="true" slot="Weapon 1" mainActiveSkill="1">
				<Gem enableGlobal2="true" level="1" enableGlobal1="true" skillId="ImpactingSteel" skillMinionItemSet="1" qualityId="Default" skillPart="1" gemId="Metadata/Items/Gems/SkillGemSplittingSteel" quality="0" enabled="true" skillPartCalcs="1" count="1" nameSpec="Splitting Steel" skillMinion="SkitterbotCold"/>
				<Gem enableGlobal2="true" level="1" enableGlobal1="true" skillId="SupportChanceToBleed" qualityId="Default" skillPart="1" gemId="Metadata/Items/Gems/SupportGemChanceToBleed" quality="0" enabled="true" count="1" nameSpec="Chance to Bleed"/>
				<Gem enableGlobal2="true" level="1" enableGlobal1="true" skillId="SupportOnslaught" qualityId="Default" gemId="Metadata/Items/Gems/SupportGemOnslaught" quality="0" enabled="true" count="1" nameSpec="Onslaught"/>
			</Skill>
			<Skill mainActiveSkillCalcs="1" includeInFullDPS="false" label="" enabled="true" mainActiveSkill="1">
				<Gem enableGlobal2="true" level="1" enableGlobal1="true" skillId="TotemMelee" qualityId="Default" gemId="Metadata/Items/Gems/SkillGemMeleeTotem" quality="0" enabled="true" count="1" nameSpec="Ancestral Protector" skillMinion="SummonedPhantasm"/>
			</Skill>
			<Skill mainActiveSkillCalcs="1" includeInFullDPS="false" label="" enabled="true" mainActiveSkill="1">
				<Gem enableGlobal2="true" level="1" enableGlobal1="true" skillId="BloodstainedBanner" qualityId="Default" gemId="Metadata/Items/Gems/SkillGemWarBanner" quality="0" enabled="true" count="1" nameSpec="War Banner"/>
			</Skill>
			<Skill mainActiveSkillCalcs="1" includeInFullDPS="false" label="" enabled="true" mainActiveSkill="1">
				<Gem enableGlobal2="true" level="1" enableGlobal1="true" skillId="SmokeMine" qualityId="Default" gemId="Metadata/Items/Gems/SkillGemSmokeMine" quality="0" enabled="true" count="1" nameSpec="Smoke Mine"/>
			</Skill>
			<Skill mainActiveSkillCalcs="1" includeInFullDPS="false" label="" enabled="true" mainActiveSkill="1">
				<Gem enableGlobal2="true" level="1" enableGlobal1="true" skillId="AccuracyAndCritsAura" qualityId="Default" gemId="Metadata/Items/Gems/SkillGemPrecision" quality="0" enabled="true" count="1" nameSpec="Precision" skillMinion="SummonedFlameGolem"/>
			</Skill>
			<Skill mainActiveSkillCalcs="1" includeInFullDPS="true" label="Shield Charge [RRG]" enabled="true" mainActiveSkill="1">
				<Gem enableGlobal2="true" level="1" enableGlobal1="true" skillId="NewShieldCharge" skillMinionItemSet="1" qualityId="Default" skillPart="1" gemId="Metadata/Items/Gems/SkillGemShieldCharge" quality="0" enabled="true" count="1" nameSpec="Shield Charge" skillMinion="SkitterbotCold"/>
				<Gem enableGlobal2="true" level="1" enableGlobal1="true" skillId="SupportFasterAttack" qualityId="Default" gemId="Metadata/Items/Gems/SupportGemFasterAttack" quality="0" enabled="true" count="1" nameSpec="Faster Attacks"/>
				<Gem enableGlobal2="true" level="1" enableGlobal1="true" skillId="SupportAddedFireDamage" qualityId="Default" gemId="Metadata/Items/Gems/SupportGemAddedFireDamage" quality="0" enabled="true" count="1" nameSpec="Added Fire Damage"/>
			</Skill>
			<Skill mainActiveSkillCalcs="1" includeInFullDPS="true" label="Poisonous Concoction [GGG]" enabled="true" slot="Body Armour" mainActiveSkill="1">
				<Gem enableGlobal2="true" skillMinionSkillCalcs="1" level="1" enableGlobal1="true" skillId="PoisonousConcoction" skillMinionSkill="1" skillMinionItemSet="1" qualityId="Default" skillPart="1" gemId="Metadata/Items/Gems/SkillGemPoisonousConcoction" quality="0" enabled="true" count="1" nameSpec="Poisonous Concoction" skillMinion="SkitterbotCold"/>
				<Gem enableGlobal2="true" level="1" enableGlobal1="true" skillId="SupportParallelProjectiles" qualityId="Default" gemId="Metadata/Items/Gems/SupportGemParallelProjectiles" quality="0" enabled="true" count="1" nameSpec="Volley"/>
				<Gem enableGlobal2="true" level="1" enableGlobal1="true" skillId="SupportLesserMultipleProjectiles" qualityId="Default" gemId="Metadata/Items/Gems/SupportGemLesserMultipleProjectiles" quality="0" enabled="true" count="1" nameSpec="Lesser Multiple Projectiles"/>
			</Skill>
		</SkillSet>
	</Skills>
	<Tree activeSpec="1">
		<Spec ascendClassId="0" masteryEffects="" nodes="47389,30691,34009,476,48807,54776,60002,28265,59718,30155,5612,50986,35568,50360,51856" treeVersion="3_19" classId="4">
			<URL>
				https://www.pathofexile.com/passive-skill-tree/AAAABgQADrkdd-OE2QHcvqfV-OpibmnpRnXLFeyK8MS4ypAAAA==
			</URL>
			<Sockets/>
		</Spec>
	</Tree>
	<Notes>
		
	</Notes>
	<TreeView searchStr="" zoomY="-614.0936" showHeatMap="false" zoomLevel="7" showStatDifferences="true" zoomX="-13.276"/>
	<Items activeItemSet="1" useSecondWeaponSet="true">
		<Item id="1">
			Rarity: NORMAL
Jade Hatchet
Quality: 20
Sockets: R-R-R
LevelReq: 6
Implicits: 0
		</Item>
		<Item id="2">
			Rarity: NORMAL
Corroded Tower Shield
Armour: 56
ArmourBasePercentile: 0.9697
Quality: 20
Sockets: R-R-R
LevelReq: 5
Implicits: 1
{tags:resource,life}{range:0.5}+(10-20) to maximum Life
			<ModRange range="0.5" id="1"/>
		</Item>
		<Item id="3">
			Rarity: NORMAL
Tricorne
Evasion: 83
EvasionBasePercentile: 1
Quality: 20
Sockets: G-G-G-G
LevelReq: 10
Implicits: 0
		</Item>
		<Item id="4">
			Rarity: NORMAL
Light Brigandine
Armour: 76
ArmourBasePercentile: 1
Evasion: 76
EvasionBasePercentile: 1
Quality: 20
Sockets: G-G-G-G-G-G
LevelReq: 8
Implicits: 0
		</Item>
		<Item id="5">
			Rarity: NORMAL
Goathide Gloves
Evasion: 50
EvasionBasePercentile: 0.9667
Quality: 20
Sockets: G-G-G-G
LevelReq: 9
Implicits: 0
		</Item>
		<Item id="6">
			Rarity: NORMAL
Rawhide Boots
Evasion: 22
EvasionBasePercentile: 1
Quality: 20
Sockets: G-G-G-G
Implicits: 0
		</Item>
		<Item id="7">
			Rarity: NORMAL
Paua Amulet
Quality: 0
Implicits: 1
{tags:resource,mana}{range:0.5}(20-30)% increased Mana Regeneration Rate
			<ModRange range="0.5" id="1"/>
		</Item>
		<Item id="8">
			Rarity: NORMAL
Paua Ring
Quality: 0
Implicits: 1
{tags:resource,mana}{range:0.5}+(20-30) to maximum Mana
			<ModRange range="0.5" id="1"/>
		</Item>
		<Item id="9">
			Rarity: NORMAL
Coral Ring
Quality: 0
Implicits: 1
{tags:resource,life}{range:0.5}+(20-30) to maximum Life
			<ModRange range="0.5" id="1"/>
		</Item>
		<Item id="10">
			Rarity: NORMAL
Leather Belt
Quality: 0
LevelReq: 8
Implicits: 1
{tags:resource,life}{range:0.5}+(25-40) to maximum Life
			<ModRange range="0.5" id="1"/>
		</Item>
		<Item id="11">
			Rarity: NORMAL
Medium Mana Flask
Quality: 20
LevelReq: 3
Implicits: 0
		</Item>
		<Item id="12">
			Rarity: NORMAL
Medium Mana Flask
Quality: 20
LevelReq: 3
Implicits: 0
		</Item>
		<Item id="13">
			Rarity: NORMAL
Medium Life Flask
Quality: 20
LevelReq: 3
Implicits: 0
		</Item>
		<Item id="14">
			Rarity: NORMAL
Medium Life Flask
Quality: 20
LevelReq: 3
Implicits: 0
		</Item>
		<Item id="15">
			Rarity: NORMAL
Quicksilver Flask
Quality: 20
LevelReq: 4
Implicits: 0
		</Item>
		<Slot name="Weapon 1" itemId="1"/>
		<Slot name="Flask 3" itemId="13"/>
		<Slot name="Gloves" itemId="5"/>
		<Slot name="Belt" itemId="10"/>
		<Slot name="Flask 5" itemId="15"/>
		<Slot name="Helmet" itemId="3"/>
		<Slot name="Flask 1" itemId="11"/>
		<Slot name="Flask 4" itemId="14"/>
		<Slot name="Flask 2" itemId="12"/>
		<Slot name="Weapon 2" itemId="2"/>
		<Slot name="Weapon 2 Swap" itemId="2"/>
		<Slot name="Ring 2" itemId="9"/>
		<Slot name="Body Armour" itemId="4"/>
		<Slot name="Ring 1" itemId="8"/>
		<Slot name="Boots" itemId="6"/>
		<Slot name="Amulet" itemId="7"/>
		<ItemSet useSecondWeaponSet="true" id="1">
			<Slot name="Weapon 1Swap Abyssal Socket 5" itemId="0"/>
			<Slot name="Weapon 1 Abyssal Socket 2" itemId="0"/>
			<Slot name="Weapon 1" itemId="1"/>
			<Slot name="Boots Abyssal Socket 5" itemId="0"/>
			<Slot name="Weapon 1Swap Abyssal Socket 2" itemId="0"/>
			<Slot name="Belt Abyssal Socket 2" itemId="0"/>
			<Slot name="Flask 3" itemId="13"/>
			<Slot name="Weapon 2Swap Abyssal Socket 3" itemId="0"/>
			<Slot name="Weapon 1 Abyssal Socket 5" itemId="0"/>
			<Slot name="Weapon 2 Abyssal Socket 5" itemId="0"/>
			<Slot name="Weapon 2 Abyssal Socket 4" itemId="0"/>
			<Slot name="Weapon 1 Abyssal Socket 6" itemId="0"/>
			<Slot name="Weapon 2 Abyssal Socket 6" itemId="0"/>
			<Slot name="Weapon 2Swap Abyssal Socket 1" itemId="0"/>
			<Slot name="Boots Abyssal Socket 3" itemId="0"/>
			<Slot name="Helmet Abyssal Socket 1" itemId="0"/>
			<Slot name="Belt Abyssal Socket 6" itemId="0"/>
			<Slot name="Helmet Abyssal Socket 2" itemId="0"/>
			<Slot name="Gloves" itemId="5"/>
			<Slot name="Helmet Abyssal Socket 3" itemId="0"/>
			<Slot name="Weapon 1Swap Abyssal Socket 1" itemId="0"/>
			<Slot name="Helmet Abyssal Socket 4" itemId="0"/>
			<Slot name="Weapon 2 Abyssal Socket 1" itemId="0"/>
			<Slot name="Weapon 1 Abyssal Socket 4" itemId="0"/>
			<Slot name="Belt" itemId="10"/>
			<Slot name="Gloves Abyssal Socket 4" itemId="0"/>
			<Slot name="Boots Abyssal Socket 4" itemId="0"/>
			<Slot name="Weapon 2 Abyssal Socket 2" itemId="0"/>
			<Slot name="Flask 5" itemId="15"/>
			<Slot name="Boots Abyssal Socket 2" itemId="0"/>
			<Slot name="Belt Abyssal Socket 3" itemId="0"/>
			<Slot name="Body Armour Abyssal Socket 1" itemId="0"/>
			<Slot name="Gloves Abyssal Socket 1" itemId="0"/>
			<Slot name="Helmet Abyssal Socket 5" itemId="0"/>
			<Slot name="Helmet Abyssal Socket 6" itemId="0"/>
			<Slot name="Helmet" itemId="3"/>
			<Slot name="Flask 1" itemId="11"/>
			<Slot name="Gloves Abyssal Socket 5" itemId="0"/>
			<Slot name="Body Armour Abyssal Socket 2" itemId="0"/>
			<Slot name="Boots Abyssal Socket 6" itemId="0"/>
			<Slot name="Weapon 1 Abyssal Socket 3" itemId="0"/>
			<Slot name="Weapon 2 Abyssal Socket 3" itemId="0"/>
			<Slot name="Belt Abyssal Socket 4" itemId="0"/>
			<Slot name="Weapon 2Swap Abyssal Socket 2" itemId="0"/>
			<Slot name="Belt Abyssal Socket 1" itemId="0"/>
			<Slot name="Body Armour Abyssal Socket 3" itemId="0"/>
			<Slot name="Flask 4" itemId="14"/>
			<Slot name="Flask 2" itemId="12"/>
			<Slot name="Belt Abyssal Socket 5" itemId="0"/>
			<Slot name="Weapon 1Swap Abyssal Socket 3" itemId="0"/>
			<Slot name="Weapon 2" itemId="2"/>
			<Slot name="Weapon 2Swap Abyssal Socket 6" itemId="0"/>
			<Slot name="Boots Abyssal Socket 1" itemId="0"/>
			<Slot name="Body Armour Abyssal Socket 4" itemId="0"/>
			<Slot name="Weapon 2Swap Abyssal Socket 4" itemId="0"/>
			<Slot name="Weapon 2 Swap" itemId="2"/>
			<Slot name="Weapon 1 Swap" itemId="0"/>
			<Slot name="Weapon 1Swap Abyssal Socket 6" itemId="0"/>
			<Slot name="Ring 2" itemId="9"/>
			<Slot name="Gloves Abyssal Socket 2" itemId="0"/>
			<Slot name="Body Armour Abyssal Socket 6" itemId="0"/>
			<Slot name="Weapon 1 Abyssal Socket 1" itemId="0"/>
			<Slot name="Body Armour" itemId="4"/>
			<Slot name="Gloves Abyssal Socket 3" itemId="0"/>
			<Slot name="Ring 1" itemId="8"/>
			<Slot name="Weapon 1Swap Abyssal Socket 4" itemId="0"/>
			<Slot name="Body Armour Abyssal Socket 5" itemId="0"/>
			<Slot name="Gloves Abyssal Socket 6" itemId="0"/>
			<Slot name="Boots" itemId="6"/>
			<Slot name="Weapon 2Swap Abyssal Socket 5" itemId="0"/>
			<Slot name="Amulet" itemId="7"/>
		</ItemSet>
	</Items>
	<Config>
		<Input name="pantheonMinorGod" string="None"/>
		<Input name="enemyIsBoss" string="None"/>
		<Input name="pantheonMajorGod" string="None"/>
		<Input name="bandit" string="None"/>
		<Placeholder name="enemySpeed" number="700"/>
		<Placeholder name="enemyCritDamage" number="30"/>
		<Placeholder name="enemyCritChance" number="5"/>
		<Placeholder name="enemyPhysicalDamage" number="20"/>
	</Config>
</PathOfBuilding>
